netconf_console/__init__.py
netconf_console/completions.py
netconf_console/ncc.py
netconf_console/nctransport.py
netconf_console/operations.py
netconf_console2-3.0.1.dist-info/AUTHORS
netconf_console2-3.0.1.dist-info/LICENSE.txt
netconf_console2-3.0.1.dist-info/METADATA
netconf_console2-3.0.1.dist-info/WHEEL
netconf_console2-3.0.1.dist-info/entry_points.txt
netconf_console2-3.0.1.dist-info/pbr.json
netconf_console2-3.0.1.dist-info/top_level.txt
netconf_console2-3.0.1.dist-info/RECORD
