Metadata-Version: 2.1
Name: netconf-console2
Version: 3.0.1
Summary: Netconf client CLI tool and interactive console
Home-page: https://bitbucket.org/martin_volf/ncc
Author: Martin Volf
Author-email: martin.volf@cetin.cz
License: MIT
Keywords: NETCONF CLI client
Platform: UNKNOWN
Classifier: Development Status :: 5 - Production/Stable
Classifier: Intended Audience :: Developers
Classifier: Intended Audience :: System Administrators
Classifier: Intended Audience :: Telecommunications Industry
Classifier: Topic :: System :: Networking
Classifier: Topic :: System :: Networking :: Monitoring
Classifier: License :: OSI Approved :: MIT License
Classifier: Programming Language :: Python :: 2.7
Classifier: Programming Language :: Python :: 3.4
Classifier: Programming Language :: Python :: 3.5
License-File: LICENSE.txt
License-File: AUTHORS
Requires-Dist: ncclient >=0.6.15
Requires-Dist: paramiko >=2.5.0
